consql/__init__.py
consql/_db.py
consql/_json.py
consql/_sql.py
consql/coerces.py
consql/errors.py
consql/main.py
consql/model.py
consql/table.py
consql/types.py
consql-0.19.dist-info/LICENSE
consql-0.19.dist-info/METADATA
consql-0.19.dist-info/WHEEL
consql-0.19.dist-info/top_level.txt
consql-0.19.dist-info/RECORD
