Metadata-Version: 2.1
Name: consql
Version: 0.19
Summary: PostgreSQL Async ORM for Python
Home-page: https://github.com/kosyachniy/consql
Author: Alexey Poloz
Author-email: polozhev@mail.ru
License: MIT
Project-URL: Source, https://github.com/kosyachniy/consql
Keywords: async,orm,python,postgresql,sql,types,checking,oop
Classifier: Development Status :: 4 - Beta
Classifier: Environment :: Console
Classifier: Intended Audience :: Developers
Classifier: Topic :: Software Development :: Libraries :: Application Frameworks
Classifier: License :: OSI Approved :: MIT License
Classifier: Programming Language :: Python :: 3
Classifier: Operating System :: OS Independent
Requires-Python: >=3.7, <4
License-File: LICENSE
Requires-Dist: asyncpg (==0.27.0)
Requires-Dist: libdev (>=0.44)
Requires-Dist: jinja2 (==3.1.2)
Requires-Dist: orjson (==3.8.3)
Requires-Dist: pydantic (==1.10.2)
